tanuky/__init__.py
tanuky/tanuky.py
tanuky-1.3.1.dist-info/LICENSE
tanuky-1.3.1.dist-info/METADATA
tanuky-1.3.1.dist-info/WHEEL
tanuky-1.3.1.dist-info/top_level.txt
tanuky-1.3.1.dist-info/RECORD
