Metadata-Version: 2.1
Name: tanuky
Version: 1.3.1
Summary: simple & flexible SSG
Home-page: https://github.com/laddge/tanuky
Author: Laddge
Author-email: dev.laddge@gmail.com
License: MIT
Platform: UNKNOWN
Requires-Dist: Jinja2
Requires-Dist: Markdown (==3.3.6)
Requires-Dist: PyYAML (==5.3.1)
Requires-Dist: tqdm (==4.63.0)
